pycam_stu/__init__.py
pycam_stu/core.py
pycam_stu-0.1.1.dist-info/METADATA
pycam_stu-0.1.1.dist-info/WHEEL
pycam_stu-0.1.1.dist-info/top_level.txt
pycam_stu-0.1.1.dist-info/RECORD
